mentra/__init__.py
mentra/ai/__init__.py
mentra/ai/application/__init__.py
mentra/ai/domain/__init__.py
mentra/ai/infrastructure/__init__.py
mentra/cli/__init__.py
mentra/cli/application/__init__.py
mentra/cli/domain/__init__.py
mentra/cli/infrastructure/__init__.py
mentra/config/__init__.py
mentra/config/application/__init__.py
mentra/config/domain/__init__.py
mentra/config/infrastructure/__init__.py
mentra/logger/__init__.py
mentra/logger/application/__init__.py
mentra/logger/domain/__init__.py
mentra/logger/infrastructure/__init__.py
mentra/metrics/__init__.py
mentra/metrics/application/__init__.py
mentra/metrics/domain/__init__.py
mentra/metrics/infrastructure/__init__.py
mentra/orchestration/__init__.py
mentra/orchestration/application/__init__.py
mentra/orchestration/domain/__init__.py
mentra/orchestration/infrastructure/__init__.py
mentra/reporting/__init__.py
mentra/reporting/application/__init__.py
mentra/reporting/domain/__init__.py
mentra/reporting/infrastructure/__init__.py
mentra/review/__init__.py
mentra/review/application/__init__.py
mentra/review/domain/__init__.py
mentra/review/infrastructure/__init__.py
mentra/shared/__init__.py
mentra/shared/application/__init__.py
mentra/shared/domain/__init__.py
mentra/shared/infrastructure/__init__.py
mentra/storage/__init__.py
mentra/storage/application/__init__.py
mentra/storage/domain/__init__.py
mentra/storage/infrastructure/__init__.py
mentra/svc/__init__.py
mentra/svc/application/__init__.py
mentra/svc/domain/__init__.py
mentra/svc/infrastructure/__init__.py
mentra-0.1.0.dist-info/METADATA
mentra-0.1.0.dist-info/WHEEL
mentra-0.1.0.dist-info/RECORD
