Metadata-Version: 2.4
Name: mentra
Version: 0.1.0
Summary: AI-powered assistant that automates code reviews and makes merging faster and more reliable.
License: MIT
Keywords: ai,code-review,merge,automation,developer-tools,lint,python
Author: Oleg Patsay
Author-email: smmartbiz@gmail.com
Requires-Python: >=3.13,<4.0
Classifier: Development Status :: 3 - Alpha
Classifier: Intended Audience :: Developers
Classifier: License :: OSI Approved :: MIT License
Classifier: Operating System :: OS Independent
Classifier: Programming Language :: Python :: 3
Classifier: Programming Language :: Python :: 3.13
Classifier: Programming Language :: Python :: 3.14
Classifier: Topic :: Software Development :: Quality Assurance
Classifier: Topic :: Software Development :: Version Control :: Git
Project-URL: Author, https://opatsay.com
Project-URL: Documentation, https://github.com/tenqz/mentra#readme
Project-URL: Homepage, https://github.com/tenqz/mentra
Project-URL: Issues, https://github.com/tenqz/mentra/issues
Project-URL: Repository, https://github.com/tenqz/mentra
